dns_unbound_cache_reader/__init__.py
dns_unbound_cache_reader/dns_unbound_cache_reader.py
dns_unbound_cache_reader-0.6.0.dist-info/licenses/LICENSE
dns_unbound_cache_reader-0.6.0.dist-info/METADATA
dns_unbound_cache_reader-0.6.0.dist-info/WHEEL
dns_unbound_cache_reader-0.6.0.dist-info/top_level.txt
dns_unbound_cache_reader-0.6.0.dist-info/RECORD
