Metadata-Version: 2.4
Name: dns-unbound-cache-reader
Version: 0.6.0
Summary: Read DNS cache from unbound
Author-email: François De Keersmaeker <francois.dekeersmaeker+github@proton.me>
Maintainer-email: François De Keersmaeker <francois.dekeersmaeker+github@proton.me>
License-Expression: GPL-3.0-or-later
Project-URL: Homepage, https://github.com/smart-home-network-security/dns-unbound-cache-reader
Project-URL: Source, https://github.com/smart-home-network-security/dns-unbound-cache-reader
Keywords: network,dns,unbound
Classifier: Development Status :: 3 - Alpha
Classifier: Programming Language :: Python :: 3
Classifier: Programming Language :: Python :: 3.8
Classifier: Programming Language :: Python :: 3.9
Classifier: Programming Language :: Python :: 3.10
Classifier: Programming Language :: Python :: 3.11
Classifier: Programming Language :: Python :: 3.12
Classifier: Programming Language :: Python :: 3 :: Only
Classifier: Operating System :: OS Independent
Requires-Python: >=3.8
License-File: LICENSE
Requires-Dist: fabric
Dynamic: license-file
